elan_vad/__init__.py
elan_vad/cli.py
elan_vad/vad.py
elan_vad-0.2.0.dist-info/entry_points.txt
elan_vad-0.2.0.dist-info/WHEEL
elan_vad-0.2.0.dist-info/METADATA
elan_vad-0.2.0.dist-info/RECORD
