Metadata-Version: 2.1
Name: elan-vad
Version: 0.2.0
Summary: A utility library to perform Voice Audio Detection on .wav files, write these sections to an elan file, and optionally cluster annotations on a given tier based on the VAD sections.
Home-page: https://github.com/CoEDL/elan-vad
Keywords: Elan,VAD,Voice,Audio,Detection
Author: Harry Keightley
Author-email: harrykeightley@outlook.com
Requires-Python: >=3.9,<4.0
Classifier: Programming Language :: Python :: 3
Classifier: Programming Language :: Python :: 3.10
Classifier: Programming Language :: Python :: 3.9
Requires-Dist: numpy (>=1.23.1,<2.0.0)
Requires-Dist: pympi-ling (>=1.70.2,<2.0.0)
Requires-Dist: torch (>=1.12.0,<2.0.0)
Requires-Dist: torchaudio (>=0.12.0,<0.13.0)
Project-URL: Repository, https://github.com/CoEDL/elan-vad
